dfactory/VERSION
dfactory/__init__.py
dfactory/core/__init__.py
dfactory/core/base.py
dfactory/core/pipeline.py
dfactory/core/utils.py
dfactory/handlers/__init__.py
dfactory/handlers/converters.py
dfactory/handlers/filters.py
dfactory/handlers/keymatcher.py
dfactory/handlers/logichandlers.py
dfactory/handlers/matches.py
dfactory/handlers/updaters.py
dfactory/seeders/__init__.py
dfactory/seeders/csvseeder.py
dfactory/seeders/jsonseeder.py
dfactory/strings/__init__.py
dfactory/strings/cutter.py
dfactory/strings/formatter.py
dfactory/utils/__init__.py
dfactory/utils/jsonutils.py
dfactory/writers/__init__.py
dfactory/writers/csvwriter.py
dfactory/writers/jsonwriter.py
dfactory-0.1.7.dist-info/METADATA
dfactory-0.1.7.dist-info/WHEEL
dfactory-0.1.7.dist-info/entry_points.txt
dfactory-0.1.7.dist-info/top_level.txt
dfactory-0.1.7.dist-info/RECORD
