Metadata-Version: 2.1
Name: dfactory
Version: 0.1.7
Summary: a data pipeline framework
Home-page: https://github.com/skiloop/dfactory
Author: skiloop
Maintainer: skiloop
Maintainer-email: skiloop@gmail.com
License: MIT
Project-URL: Source, https://github.com/skiloop/dfactory
Project-URL: Tracker, https://github.com/skiloop/dfactory/issues
Classifier: Development Status :: 5 - Production/Stable
Classifier: Environment :: Console
Classifier: Intended Audience :: Developers
Classifier: License :: OSI Approved :: MIT License
Classifier: Operating System :: OS Independent
Classifier: Programming Language :: Python
Classifier: Programming Language :: Python :: 3
Classifier: Programming Language :: Python :: 3.7
Classifier: Programming Language :: Python :: 3.8
Classifier: Programming Language :: Python :: 3.9
Classifier: Programming Language :: Python :: 3.10
Classifier: Topic :: Software Development :: Libraries :: Application Frameworks
Classifier: Topic :: Software Development :: Libraries :: Python Modules
Requires-Python: >=3.6
